mdit_py_toc/__init__.py
mdit_py_toc/__version__.py
mdit_py_toc/plugin.py
mdit_py_toc-1.0.0.dist-info/LICENSE
mdit_py_toc-1.0.0.dist-info/METADATA
mdit_py_toc-1.0.0.dist-info/WHEEL
mdit_py_toc-1.0.0.dist-info/RECORD
