Metadata-Version: 2.1
Name: mdit-py-toc
Version: 1.0.0
Summary: A table of contents (TOC) plugin for markdown-it-py
Home-page: https://github.com/bjoernricks/mdit-py-toc
License: MIT
Author: Björn Ricks
Author-email: bjoern.ricks@greenbone.net
Requires-Python: >=3.9,<4.0
Classifier: Development Status :: 4 - Beta
Classifier: Environment :: Console
Classifier: Intended Audience :: Developers
Classifier: License :: OSI Approved :: MIT License
Classifier: Operating System :: OS Independent
Classifier: Programming Language :: Python :: 3
Classifier: Programming Language :: Python :: 3.9
Classifier: Programming Language :: Python :: 3.10
Classifier: Programming Language :: Python :: 3.11
Classifier: Programming Language :: Python :: 3.12
Classifier: Topic :: Software Development :: Libraries :: Python Modules
Classifier: Topic :: Text Processing :: Markup :: Markdown
Requires-Dist: markdown-it-py (>=3.0.0)
Project-URL: Repository, https://github.com/bjoernricks/mdit-py-toc/
